{
    "post": "/alerts/queues",
    "contentType": "application/vnd.sas.collection.triage.queue+json",
    "body": [
        [
            {
                "alertMaxDurationInQueue": 24,
                "defaultFlag": false,
                "domainID": "sfd_payment_fraud",
                "id": "sfd_debit_card_not_present",
                "localizedName": "Card Not Present",
                "name": "Card Not Present",
                "optLockVersion": -1,
                "reactivationEnabled": false,
                "routingEnabled": true,
                "routingPriority": 1,
                "routingRule": "enrichmentData.sfd_dec_outcome_enrch!=10\u0026\u0026alertType==\"sfd_debitcard\"\u0026\u0026enrichmentData.sfd_cf_cardPresInd_enrch==\"1\"\u0026\u0026enrichmentData.sfd_cf_usdAmt_enrch \u003e= 100.00",
                "serviceEnabled": true,
                "servicePriority": 1,
                "serviceSortFieldOrder": "creationTimeStamp:ascending",
                "stickyFlag": false,
                "triageTypeID": "sfd_debit_card_fraud",
                "version": 1
            },
            {
                "alertMaxDurationInQueue": 24,
                "defaultFlag": false,
                "domainID": "sfd_payment_fraud",
                "id": "sfd_credit_card_not_present",
                "localizedName": "Card Not Present",
                "name": "Card Not Present",
                "optLockVersion": -1,
                "reactivationEnabled": false,
                "routingEnabled": true,
                "routingPriority": 2,
                "routingRule": "enrichmentData.sfd_dec_outcome_enrch!=10\u0026\u0026alertType==\"sfd_creditcard\"\u0026\u0026enrichmentData.sfd_cf_cardPresInd_enrch==\"1\"\u0026\u0026enrichmentData.sfd_cf_usdAmt_enrch \u003e= 100.00",
                "serviceEnabled": true,
                "servicePriority": 2,
                "serviceSortFieldOrder": "creationTimeStamp:ascending",
                "stickyFlag": false,
                "triageTypeID": "sfd_credit_card_fraud",
                "version": 1
            },
            {
                "alertMaxDurationInQueue": 24,
                "defaultFlag": false,
                "domainID": "sfd_payment_fraud",
                "id": "sfd_credit_card_present",
                "localizedName": "Card Present",
                "name": "Card Present",
                "optLockVersion": -1,
                "reactivationEnabled": false,
                "routingEnabled": true,
                "routingPriority": 3,
                "routingRule": "enrichmentData.sfd_dec_outcome_enrch!=10\u0026\u0026alertType==\"sfd_creditcard\"\u0026\u0026enrichmentData.sfd_cf_cardPresInd_enrch==\"0\"\u0026\u0026enrichmentData.sfd_cf_usdAmt_enrch \u003e= 100.00",
                "serviceEnabled": true,
                "servicePriority": 3,
                "serviceSortFieldOrder": "creationTimeStamp:ascending",
                "stickyFlag": false,
                "triageTypeID": "sfd_credit_card_fraud",
                "version": 1
            },
            {
                "alertMaxDurationInQueue": 24,
                "defaultFlag": false,
                "domainID": "sfd_payment_fraud",
                "id": "sfd_debit_card_present",
                "localizedName": "Card Present",
                "name": "Card Present",
                "optLockVersion": -1,
                "reactivationEnabled": false,
                "routingEnabled": true,
                "routingPriority": 4,
                "routingRule": "enrichmentData.sfd_dec_outcome_enrch!=10\u0026\u0026alertType==\"sfd_debitcard\"\u0026\u0026enrichmentData.sfd_cf_cardPresInd_enrch==\"0\"\u0026\u0026enrichmentData.sfd_cf_usdAmt_enrch \u003e= 100.00",
                "serviceEnabled": true,
                "servicePriority": 4,
                "serviceSortFieldOrder": "creationTimeStamp:ascending",
                "stickyFlag": false,
                "triageTypeID": "sfd_debit_card_fraud",
                "version": 1
            },
            {
                "alertMaxDurationInQueue": 24,
                "defaultFlag": true,
                "domainID": "domain_default",
                "groupID": "SASTriageUsers",
                "id": "queue_default",
                "localizedName": "Default Queue",
                "name": "Default Queue",
                "optLockVersion": -1,
                "reactivationEnabled": false,
                "routingEnabled": true,
                "routingPriority": 5,
                "serviceEnabled": true,
                "servicePriority": 5,
                "serviceSortFieldOrder": "creationTimeStamp:ascending",
                "stickyFlag": false,
                "triageTypeID": "triage_type_default",
                "version": 1
            },
            {
                "alertMaxDurationInQueue": 24,
                "defaultFlag": false,
                "domainID": "sfd_payment_fraud",
                "id": "sfd_vip_payment_fraud",
                "localizedName": "High Value",
                "name": "High Value",
                "optLockVersion": -1,
                "reactivationEnabled": false,
                "routingEnabled": true,
                "routingPriority": 6,
                "routingRule": "enrichmentData.sfd_dec_outcome_enrch!=10\u0026\u0026alertType==\"sfd_debitacc\"\u0026\u0026enrichmentData.sfd_cus_type_enrch==\"VIP\"\u0026\u0026enrichmentData.sfd_cf_usdAmt_enrch \u003e= 100.00",
                "serviceEnabled": true,
                "servicePriority": 6,
                "serviceSortFieldOrder": "creationTimeStamp:ascending",
                "stickyFlag": false,
                "triageTypeID": "sfd_vip_payment_fraud",
                "version": 1
            },
            {
                "alertMaxDurationInQueue": 24,
                "defaultFlag": false,
                "domainID": "sfd_payment_fraud",
                "id": "sfd_high_payment_fraud",
                "localizedName": "High Value",
                "name": "High Value",
                "optLockVersion": -1,
                "reactivationEnabled": false,
                "routingEnabled": true,
                "routingPriority": 7,
                "routingRule": "enrichmentData.sfd_dec_outcome_enrch!=10\u0026\u0026alertType==\"sfd_debitacc\"\u0026\u0026enrichmentData.sfd_cf_usdAmt_enrch \u003e= 1000.00",
                "serviceEnabled": true,
                "servicePriority": 7,
                "serviceSortFieldOrder": "creationTimeStamp:ascending",
                "stickyFlag": false,
                "triageTypeID": "sfd_payment_fraud",
                "version": 1
            },
            {
                "alertMaxDurationInQueue": 24,
                "defaultFlag": false,
                "domainID": "sfd_payment_fraud",
                "groupID": "Fraud_Decisioning_Users_Triage_Payment_Fraud",
                "id": "sfd_high_other_payment_fraud",
                "localizedName": "High Value - Others",
                "name": "High Value - Others",
                "optLockVersion": -1,
                "reactivationEnabled": false,
                "routingEnabled": true,
                "routingPriority": 8,
                "serviceEnabled": true,
                "servicePriority": 8,
                "serviceSortFieldOrder": "creationTimeStamp:ascending",
                "stickyFlag": false,
                "triageTypeID": "sfd_payment_fraud",
                "version": 1
            },
            {
                "alertMaxDurationInQueue": 24,
                "defaultFlag": false,
                "domainID": "sfd_payment_fraud",
                "groupID": "Fraud_Decisioning_Administrator",
                "id": "sfd_payment_fraud",
                "localizedName": "Payment Fraud",
                "name": "Payment Fraud",
                "optLockVersion": -1,
                "reactivationEnabled": false,
                "routingEnabled": true,
                "routingPriority": 9,
                "serviceEnabled": true,
                "servicePriority": 9,
                "serviceSortFieldOrder": "creationTimeStamp:ascending",
                "stickyFlag": false,
                "triageTypeID": "sfd_payment_fraud",
                "version": 1
            },
            {
                "alertMaxDurationInQueue": 24,
                "defaultFlag": false,
                "domainID": "sfd_payment_fraud",
                "id": "test_queue",
                "localizedName": "Card Not Present",
                "name": "Card Not Present",
                "optLockVersion": -1,
                "reactivationEnabled": false,
                "routingEnabled": false,
                "routingPriority": 10,
                "routingRule": "",
                "serviceEnabled": true,
                "servicePriority": 10,
                "serviceSortFieldOrder": "creationTimeStamp:ascending",
                "stickyFlag": false,
                "triageTypeID": "sfd_debit_card_fraud",
                "version": 1
            }
        ]
    ]
}


